statix/__init__.py
statix/background.py
statix/bayesian_blocks.py
statix/camera.py
statix/counts.py
statix/ebands.py
statix/exposure.py
statix/image.py
statix/inpaint.py
statix/mca.py
statix/mca_transforms.py
statix/plotting.py
statix/psf.py
statix/source_detection.py
statix/timebins.py
statix/utils.py
statix/xmmsas.py
statix/data/psf_EMOS1_1000.fits
statix/data/psf_EMOS1_1500.fits
statix/data/psf_EMOS1_2000.fits
statix/data/psf_EMOS1_2750.fits
statix/data/psf_EMOS1_3500.fits
statix/data/psf_EMOS1_4250.fits
statix/data/psf_EMOS1_6000.fits
statix/data/psf_EMOS1_8500.fits
statix/data/psf_EMOS2_1000.fits
statix/data/psf_EMOS2_1500.fits
statix/data/psf_EMOS2_2000.fits
statix/data/psf_EMOS2_2750.fits
statix/data/psf_EMOS2_3500.fits
statix/data/psf_EMOS2_4250.fits
statix/data/psf_EMOS2_6000.fits
statix/data/psf_EMOS2_8500.fits
statix/data/psf_EPN_1000.fits
statix/data/psf_EPN_1500.fits
statix/data/psf_EPN_2000.fits
statix/data/psf_EPN_2750.fits
statix/data/psf_EPN_3500.fits
statix/data/psf_EPN_4250.fits
statix/data/psf_EPN_6000.fits
statix/data/psf_EPN_8500.fits
xstatix-1.2.0.dist-info/licenses/LICENSE
xstatix-1.2.0.dist-info/METADATA
xstatix-1.2.0.dist-info/WHEEL
xstatix-1.2.0.dist-info/top_level.txt
xstatix-1.2.0.dist-info/RECORD
