Metadata-Version: 2.4
Name: xstatix
Version: 1.2.0
Summary: Space and Time Algorithm for Transients In X-rays
Author-email: Angel Ruiz <angel.ruizca@gmail.com>, Antonis Georgakakis <age@noa.gr>
Project-URL: Homepage, https://github.com/ruizca/statix
Classifier: Programming Language :: Python :: 3
Classifier: License :: OSI Approved :: BSD License
Classifier: Operating System :: POSIX :: Linux
Classifier: Intended Audience :: Science/Research
Classifier: Topic :: Scientific/Engineering :: Astronomy
Requires-Python: >=3.10
License-File: LICENSE
Requires-Dist: astropy
Requires-Dist: joblib
Requires-Dist: numpy
Requires-Dist: mocpy
Requires-Dist: msvst
Requires-Dist: photutils
Requires-Dist: PyWavelets
Requires-Dist: pxsas
Requires-Dist: regions
Requires-Dist: rich
Requires-Dist: scipy
Dynamic: license-file
